{"sensor1":{"sensor":"Light","number":"18:45:12 GMT-0500 (Eastern Standard Time)","type":5,"id":"18:45:12 GMT-0500 (Eastern Standard Time)","reading":"18:45:12 GMT-0500 (Eastern Standard Time)"},"sensor2":{"sensor":"Laser","number":"18:45:12 GMT-0500 (Eastern Standard Time)","type":"18:45:12 GMT-0500 (Eastern Standard Time)","id":0,"reading":"18:45:12 GMT-0500 (Eastern Standard Time)"},"sensor3":{"sensor":"Lane","number":"18:45:12 GMT-0500 (Eastern Standard Time)","type":"18:45:12 GMT-0500 (Eastern Standard Time)","id":"18:45:12 GMT-0500 (Eastern Standard Time)","reading":"18:45:12 GMT-0500 (Eastern Standard Time)"}}